minidlna_exporter/__init__.py
minidlna_exporter/minidlna_exporter.py
minidlna_exporter-0.1.2.dist-info/METADATA
minidlna_exporter-0.1.2.dist-info/RECORD
minidlna_exporter-0.1.2.dist-info/WHEEL
minidlna_exporter-0.1.2.dist-info/entry_points.txt
minidlna_exporter-0.1.2.dist-info/top_level.txt
