Metadata-Version: 2.1
Name: minidlna-exporter
Version: 0.1.2
Summary: Export minidlna metrics for prometheus
Home-page: https://github.com/dr1s/minidlna_exporter.py
Author: dr1s
License: MIT
Platform: UNKNOWN
Requires-Dist: beautifulsoup4
Requires-Dist: promethues-metrics (>=0.1.3)
